odoo10_addon_account_bank_statement_import_ofx-10.0.1.0.0-py2.7-nspkg.pth
odoo10_addon_account_bank_statement_import_ofx-10.0.1.0.0.dist-info/top_level.txt
odoo10_addon_account_bank_statement_import_ofx-10.0.1.0.0.dist-info/WHEEL
odoo10_addon_account_bank_statement_import_ofx-10.0.1.0.0.dist-info/RECORD
odoo10_addon_account_bank_statement_import_ofx-10.0.1.0.0.dist-info/metadata.json
odoo10_addon_account_bank_statement_import_ofx-10.0.1.0.0.dist-info/DESCRIPTION.rst
odoo10_addon_account_bank_statement_import_ofx-10.0.1.0.0.dist-info/METADATA
odoo10_addon_account_bank_statement_import_ofx-10.0.1.0.0.dist-info/namespace_packages.txt
odoo/addons/account_bank_statement_import_ofx/__manifest__.py
odoo/addons/account_bank_statement_import_ofx/__init__.py
odoo/addons/account_bank_statement_import_ofx/README.rst
odoo/addons/account_bank_statement_import_ofx/i18n/es.po
odoo/addons/account_bank_statement_import_ofx/i18n/account_bank_statement_import_ofx.pot
odoo/addons/account_bank_statement_import_ofx/i18n/lt_LT.po
odoo/addons/account_bank_statement_import_ofx/i18n/sl.po
odoo/addons/account_bank_statement_import_ofx/i18n/nl.po
odoo/addons/account_bank_statement_import_ofx/i18n/fr.po
odoo/addons/account_bank_statement_import_ofx/i18n/pt_BR.po
odoo/addons/account_bank_statement_import_ofx/wizard/account_bank_statement_import.py
odoo/addons/account_bank_statement_import_ofx/wizard/__init__.py
odoo/addons/account_bank_statement_import_ofx/views/view_account_bank_statement_import.xml
odoo/addons/account_bank_statement_import_ofx/tests/__init__.py
odoo/addons/account_bank_statement_import_ofx/tests/test_import_bank_statement.py
odoo/addons/account_bank_statement_import_ofx/tests/test_ofx_file/test_ofx.ofx
odoo/addons/account_bank_statement_import_ofx/static/description/icon.png
