Metadata-Version: 2.0
Name: odoo10-addon-account-bank-statement-import-ofx
Version: 10.0.1.0.0
Summary: Import OFX Bank Statement
Home-page: https://odoo-community.org/
Author: Odoo SA,Akretion,La Louve,GRAP,Odoo Community Association (OCA)
Author-email: support@odoo-community.org
License: AGPL-3
Platform: UNKNOWN
Requires-Dist: odoo (<10.1dev,>=10.0)
Requires-Dist: ofxparse
Classifier: Programming Language :: Python :: 2.7
Classifier: Framework :: Odoo
Classifier: License :: OSI Approved :: GNU Affero General Public License v3
